itkwasm_transform/__init__.py
itkwasm_transform/_version.py
itkwasm_transform/affine_ops.py
itkwasm_transform/affine_ops_async.py
itkwasm_transform/create_affine_transform.py
itkwasm_transform/create_affine_transform_async.py
itkwasm_transform/create_azimuth_elevation_to_cartesian_transform.py
itkwasm_transform/create_azimuth_elevation_to_cartesian_transform_async.py
itkwasm_transform/create_bspline_smoothing_on_update_displacement_field_transform.py
itkwasm_transform/create_bspline_smoothing_on_update_displacement_field_transform_async.py
itkwasm_transform/create_bspline_transform.py
itkwasm_transform/create_bspline_transform_async.py
itkwasm_transform/create_composite_transform.py
itkwasm_transform/create_composite_transform_async.py
itkwasm_transform/create_constant_velocity_field_transform.py
itkwasm_transform/create_constant_velocity_field_transform_async.py
itkwasm_transform/create_displacement_field_transform.py
itkwasm_transform/create_displacement_field_transform_async.py
itkwasm_transform/create_euler2d_transform.py
itkwasm_transform/create_euler2d_transform_async.py
itkwasm_transform/create_euler3d_transform.py
itkwasm_transform/create_euler3d_transform_async.py
itkwasm_transform/create_gaussian_exponential_diffeomorphic_transform.py
itkwasm_transform/create_gaussian_exponential_diffeomorphic_transform_async.py
itkwasm_transform/create_gaussian_smoothing_on_update_displacement_field_transform.py
itkwasm_transform/create_gaussian_smoothing_on_update_displacement_field_transform_async.py
itkwasm_transform/create_gaussian_smoothing_on_update_time_varying_velocity_field_transform.py
itkwasm_transform/create_gaussian_smoothing_on_update_time_varying_velocity_field_transform_async.py
itkwasm_transform/create_identity_transform.py
itkwasm_transform/create_identity_transform_async.py
itkwasm_transform/create_quaternion_rigid_transform.py
itkwasm_transform/create_quaternion_rigid_transform_async.py
itkwasm_transform/create_rigid2d_transform.py
itkwasm_transform-0.1.0.dist-info/METADATA
itkwasm_transform-0.1.0.dist-info/WHEEL
itkwasm_transform-0.1.0.dist-info/RECORD
